[{"_path":"/configuration/block/files","_dir":"block","_draft":false,"_partial":false,"_locale":"","title":"Files","description":"The files blocks configure the file serving. Can be defined multiple times as long as the base_path is unique.","_type":"markdown","_id":"content:2.configuration:4.block:files.md","_source":"content","_file":"2.configuration/4.block/files.md","_extension":"md"},{"_path":"/configuration/block/job","_dir":"block","_draft":false,"_partial":false,"_locale":"","title":"Job (Beta)","description":"The beta_job block lets you define recurring requests or sequences with an given interval. The job runs at startup\nand for every interval and has an own log type: job which represents the starting point with an uid for tracing\npurposes.","_type":"markdown","_id":"content:2.configuration:4.block:job.md","_source":"content","_file":"2.configuration/4.block/job.md","_extension":"md"}]