{"id":"7ff37b7c-23ee-476e-9e30-4baada073b97","timestamp":1747331073632,"matcher":{"static":{},"wildcard":{},"dynamic":{}},"prerendered":["/","/getting-started/beta-features","/configuration/block/basic_auth","/configuration/block/definitions","/configuration/block/defaults","/configuration/block/beta_oauth2","/configuration/expressions","/configuration/configuration-file","/getting-started/running-couper","/getting-started/examples","/configuration/modifiers","/configuration/block/backend_tls","/configuration/block/cors","/configuration/command-line","/configuration/block/api","/configuration/block/client_certificate","/configuration/block/backend","/configuration/block/endpoint","/configuration/block/environment","/configuration/block/error_handler","/configuration/block/files","/configuration/block/health","/configuration/block/job","/configuration/block/jwt","/configuration/block/oauth2","/configuration/block/openapi","/configuration/block/oidc","/configuration/block/proxy","/configuration/block/rate_limit","/configuration/block/request","/configuration/block/response","/configuration/block/saml","/configuration/block/jwt_signing_profile","/configuration/block/server_certificate","/configuration/block/server_tls","/configuration/block/server","/configuration/block/settings","/configuration/block/spa","/configuration/block/websockets","/configuration/block/token_request","/configuration/variables","/configuration/functions","/configuration/error-handling","/configuration/multiple-files","/configuration/access-control","/observation/logging","/observation/health","/observation/metrics"]}